epub_metadata/__init__.py
epub_metadata/epub.py
epub_metadata/metadata.py
epub_metadata/opf_parser.py
epub_metadata-1.0.7.dist-info/LICENSE.md
epub_metadata-1.0.7.dist-info/METADATA
epub_metadata-1.0.7.dist-info/WHEEL
epub_metadata-1.0.7.dist-info/RECORD
