Metadata-Version: 2.3
Name: epub-metadata
Version: 1.0.7
Summary: 
Author: ThanatosDi
Author-email: yykkold55tw@gmail.com
Requires-Python: >=3.9,<4.0
Classifier: Programming Language :: Python :: 3
Classifier: Programming Language :: Python :: 3.9
Classifier: Programming Language :: Python :: 3.10
Classifier: Programming Language :: Python :: 3.11
Classifier: Programming Language :: Python :: 3.12
Classifier: Programming Language :: Python :: 3.13
Requires-Dist: arrow (>=1.2.3,<2.0.0)
